README.rst
setup.py
flask_raven/__init__.py
flask_raven/config.py
flask_raven/errors.py
flask_raven/helpers.py
flask_raven/keys.py
flask_raven/resource.py
flask_raven.egg-info/PKG-INFO
flask_raven.egg-info/SOURCES.txt
flask_raven.egg-info/dependency_links.txt
flask_raven.egg-info/requires.txt
flask_raven.egg-info/top_level.txt