Metadata-Version: 1.0
Name: flask-raven
Version: 0.0.2
Summary: A flask extension for the University of Cambridge's authentication system
Home-page: http://github.com/danielchatfield/flask-raven/
Author: Daniel Chatfield
Author-email: chatfielddaniel@gmail.com
License: Artistic 2.0
Platform: any
